tracecov/__init__.py
tracecov/_version.py
tracecov/http.py
tracecov/terminal.py
tracecov/schemathesis/__init__.py
tracecov/schemathesis/handler.py
tracecov/schemathesis/options.py
tracecov-0.15.2.dist-info/METADATA
tracecov-0.15.2.dist-info/WHEEL
tracecov-0.15.2.dist-info/RECORD
