Metadata-Version: 2.4
Name: tracecov
Version: 0.15.2
Summary: Schema-level API coverage down to individual keywords.
Project-URL: Homepage, https://docs.tracecov.sh
Project-URL: Documentation, https://docs.tracecov.sh
Author-email: TraceCov Team <info@tracecov.sh>
Keywords: api,api-testing,coverage,json-schema,openapi,schema,schemathesis,swagger,testing
Classifier: Development Status :: 4 - Beta
Classifier: Intended Audience :: Developers
Classifier: Operating System :: OS Independent
Classifier: Programming Language :: Python :: 3
Classifier: Programming Language :: Python :: 3.10
Classifier: Programming Language :: Python :: 3.11
Classifier: Programming Language :: Python :: 3.12
Classifier: Programming Language :: Python :: 3.13
Classifier: Programming Language :: Python :: 3.14
Classifier: Programming Language :: Rust
Classifier: Topic :: Software Development :: Quality Assurance
Classifier: Topic :: Software Development :: Testing
Classifier: Typing :: Typed
Requires-Python: >=3.10
Requires-Dist: tracecov-community==0.15.2
